Metadata-Version: 2.1
Name: go-extension
Version: 0.0.1
Summary: Include Go packages as a Python extension module
Home-page: https://github.com/huisint/go-extension-python
Author: Shuhei Nitta
Author-email: huisintheta@gmail.com
License: MIT
Platform: UNKNOWN
Requires-Python: >=3.10
License-File: LICENSE
